mldeeptool/__init__.py
mldeeptool/public.py
mldeeptool-1.0.0.dist-info/METADATA
mldeeptool-1.0.0.dist-info/WHEEL
mldeeptool-1.0.0.dist-info/top_level.txt
mldeeptool-1.0.0.dist-info/RECORD
