Metadata-Version: 2.4
Name: mldeeptool
Version: 1.0.0
Summary: 神经网络相关工具库
Home-page: https://www.python.org
Author: mengling
Author-email: 1321443305@qq.com
Requires-Python: >=3.8
Requires-Dist: numpy
Requires-Dist: torch
Dynamic: author
Dynamic: author-email
Dynamic: home-page
Dynamic: requires-dist
Dynamic: requires-python
Dynamic: summary
